{
	"info": {
		"_postman_id": "c6329744-ab7c-49e1-8edc-853fe7429967",
		"name": "ZDtestDamian",
		"schema": "https://schema.getpostman.com/json/collection/v2.1.0/collection.json"
	},
	"item": [
		{
			"name": "GET Status",
			"event": [
				{
					"listen": "test",
					"script": {
						"exec": [
							"pm.test(\"Status code is 200\", function () {\r",
							"    pm.response.to.have.status(200);\r",
							"});"
						],
						"type": "text/javascript"
					}
				}
			],
			"request": {
				"method": "GET",
				"header": [],
				"url": {
					"raw": "{{url}}/status",
					"host": [
						"{{url}}"
					],
					"path": [
						"status"
					]
				}
			},
			"response": []
		},
		{
			"name": "GET list books",
			"event": [
				{
					"listen": "test",
					"script": {
						"exec": [
							"pm.test(\"Status code is 200\", function () {\r",
							"    pm.response.to.have.status(200);\r",
							"});"
						],
						"type": "text/javascript"
					}
				}
			],
			"request": {
				"method": "GET",
				"header": [],
				"url": {
					"raw": "{{url}}/books?limit=2",
					"host": [
						"{{url}}"
					],
					"path": [
						"books"
					],
					"query": [
						{
							"key": "limit",
							"value": "2"
						}
					]
				}
			},
			"response": []
		},
		{
			"name": "Get Single book",
			"event": [
				{
					"listen": "test",
					"script": {
						"exec": [
							"pm.test(\"Status code is 200\", function () {\r",
							"    pm.response.to.have.status(200);\r",
							"});"
						],
						"type": "text/javascript"
					}
				}
			],
			"request": {
				"method": "GET",
				"header": [],
				"url": {
					"raw": "{{url}}/books/:bookId",
					"host": [
						"{{url}}"
					],
					"path": [
						"books",
						":bookId"
					],
					"variable": [
						{
							"key": "bookId",
							"value": "1"
						}
					]
				}
			},
			"response": []
		},
		{
			"name": "POST Auth1",
			"event": [
				{
					"listen": "test",
					"script": {
						"exec": [
							"pm.test(\"Status code is 201\", function () {\r",
							"    pm.response.to.have.status(201);\r",
							"});\r",
							"\r",
							"const response = pm.response.json();\r",
							"pm.globals.set(\"tokenNew\",response.accessToken);\r",
							""
						],
						"type": "text/javascript"
					}
				}
			],
			"request": {
				"method": "POST",
				"header": [],
				"body": {
					"mode": "raw",
					"raw": "{\r\n   \"clientName\": \"Postman\",\r\n   \"clientEmail\": \"{{$randomEmail}}\"\r\n}",
					"options": {
						"raw": {
							"language": "json"
						}
					}
				},
				"url": {
					"raw": "{{url}}/api-clients/",
					"host": [
						"{{url}}"
					],
					"path": [
						"api-clients",
						""
					]
				}
			},
			"response": []
		},
		{
			"name": "POST submit order",
			"event": [
				{
					"listen": "test",
					"script": {
						"exec": [
							"pm.test(\"Status code is 201\", function () {\r",
							"    pm.response.to.have.status(201);\r",
							"});\r",
							"const response = pm.response.json();\r",
							"pm.globals.set(\"orderNew\",response.orderId);"
						],
						"type": "text/javascript"
					}
				}
			],
			"request": {
				"auth": {
					"type": "bearer",
					"bearer": [
						{
							"key": "token",
							"value": "{{tokenNew}}",
							"type": "string"
						}
					]
				},
				"method": "POST",
				"header": [],
				"body": {
					"mode": "raw",
					"raw": "{\r\n  \"bookId\": 1,\r\n  \"customerName\": \"John\"\r\n}",
					"options": {
						"raw": {
							"language": "json"
						}
					}
				},
				"url": {
					"raw": "{{url}}/orders",
					"host": [
						"{{url}}"
					],
					"path": [
						"orders"
					]
				}
			},
			"response": []
		},
		{
			"name": "GET all order",
			"event": [
				{
					"listen": "test",
					"script": {
						"exec": [
							"pm.test(\"Status code is 200\", function () {\r",
							"    pm.response.to.have.status(200);\r",
							"});"
						],
						"type": "text/javascript"
					}
				}
			],
			"request": {
				"auth": {
					"type": "bearer",
					"bearer": [
						{
							"key": "token",
							"value": "{{tokenNew}}",
							"type": "string"
						}
					]
				},
				"method": "GET",
				"header": [],
				"url": {
					"raw": "{{url}}/orders?=hkVJKRfkaophTG0tczOX1",
					"host": [
						"{{url}}"
					],
					"path": [
						"orders"
					],
					"query": [
						{
							"key": "",
							"value": "hkVJKRfkaophTG0tczOX1"
						}
					]
				}
			},
			"response": []
		},
		{
			"name": "GET order",
			"event": [
				{
					"listen": "test",
					"script": {
						"exec": [
							"pm.test(\"Status code is 200\", function () {\r",
							"    pm.response.to.have.status(200);\r",
							"});"
						],
						"type": "text/javascript"
					}
				}
			],
			"protocolProfileBehavior": {
				"disableBodyPruning": true
			},
			"request": {
				"auth": {
					"type": "bearer",
					"bearer": [
						{
							"key": "token",
							"value": "{{tokenNew}}",
							"type": "string"
						}
					]
				},
				"method": "GET",
				"header": [],
				"body": {
					"mode": "raw",
					"raw": "",
					"options": {
						"raw": {
							"language": "json"
						}
					}
				},
				"url": {
					"raw": "{{url}}/orders/:orderId",
					"host": [
						"{{url}}"
					],
					"path": [
						"",
						"orders",
						":orderId"
					],
					"query": [
						{
							"key": null,
							"value": "",
							"disabled": true
						}
					],
					"variable": [
						{
							"key": "orderId",
							"value": "{{orderNew}}"
						}
					]
				}
			},
			"response": []
		},
		{
			"name": "PATCH",
			"event": [
				{
					"listen": "test",
					"script": {
						"exec": [
							"pm.test(\"Status code is 204\", function () {\r",
							"    pm.response.to.have.status(204);\r",
							"});"
						],
						"type": "text/javascript"
					}
				}
			],
			"request": {
				"auth": {
					"type": "bearer",
					"bearer": [
						{
							"key": "token",
							"value": "{{tokenNew}}",
							"type": "string"
						}
					]
				},
				"method": "PATCH",
				"header": [],
				"body": {
					"mode": "raw",
					"raw": "{\r\n  \"customerName\": \"Damian\"\r\n}",
					"options": {
						"raw": {
							"language": "json"
						}
					}
				},
				"url": {
					"raw": "{{url}}/orders/:orderId",
					"host": [
						"{{url}}"
					],
					"path": [
						"orders",
						":orderId"
					],
					"variable": [
						{
							"key": "orderId",
							"value": "{{orderNew}}"
						}
					]
				}
			},
			"response": []
		},
		{
			"name": "DELETE oa order",
			"event": [
				{
					"listen": "test",
					"script": {
						"exec": [
							"pm.test(\"Status code is 204\", function () {\r",
							"    pm.response.to.have.status(204);\r",
							"});"
						],
						"type": "text/javascript"
					}
				}
			],
			"request": {
				"auth": {
					"type": "bearer",
					"bearer": [
						{
							"key": "token",
							"value": "{{tokenNew}}",
							"type": "string"
						}
					]
				},
				"method": "DELETE",
				"header": [],
				"body": {
					"mode": "raw",
					"raw": "",
					"options": {
						"raw": {
							"language": "json"
						}
					}
				},
				"url": {
					"raw": "{{url}}/orders/:orderId",
					"host": [
						"{{url}}"
					],
					"path": [
						"orders",
						":orderId"
					],
					"variable": [
						{
							"key": "orderId",
							"value": "{{orderNew}}"
						}
					]
				}
			},
			"response": []
		}
	],
	"event": [
		{
			"listen": "prerequest",
			"script": {
				"type": "text/javascript",
				"exec": [
					""
				]
			}
		},
		{
			"listen": "test",
			"script": {
				"type": "text/javascript",
				"exec": [
					""
				]
			}
		}
	],
	"variable": [
		{
			"key": "url",
			"value": "https://simple-books-api.glitch.me",
			"type": "default"
		},
		{
			"key": "accessToken",
			"value": "",
			"type": "default"
		},
		{
			"key": "OrderID",
			"value": "hkVJKRfkaophTG0tczOX1",
			"type": "default"
		}
	]
}